main.py
alchemist_core/__init__.py
alchemist_core/audit_log.py
alchemist_core/config.py
alchemist_core/events.py
alchemist_core/session.py
alchemist_core/acquisition/__init__.py
alchemist_core/acquisition/base_acquisition.py
alchemist_core/acquisition/botorch_acquisition.py
alchemist_core/acquisition/skopt_acquisition.py
alchemist_core/data/__init__.py
alchemist_core/data/experiment_manager.py
alchemist_core/data/search_space.py
alchemist_core/models/__init__.py
alchemist_core/models/base_model.py
alchemist_core/models/botorch_model.py
alchemist_core/models/sklearn_model.py
alchemist_core/utils/__init__.py
alchemist_core/utils/doe.py
alchemist_nrel-0.3.1.dist-info/licenses/LICENSE
api/__init__.py
api/dependencies.py
api/example_client.py
api/main.py
api/run_api.py
api/middleware/__init__.py
api/middleware/error_handlers.py
api/models/__init__.py
api/models/requests.py
api/models/responses.py
api/routers/__init__.py
api/routers/acquisition.py
api/routers/experiments.py
api/routers/models.py
api/routers/sessions.py
api/routers/variables.py
api/routers/visualizations.py
api/routers/websocket.py
api/services/__init__.py
api/services/session_store.py
api/static/NEW_ICON.ico
api/static/NEW_ICON.png
api/static/NEW_LOGO_DARK.png
api/static/NEW_LOGO_LIGHT.png
api/static/index.html
api/static/vite.svg
api/static/assets/api-vcoXEqyq.js
api/static/assets/index-DWfIKU9j.js
api/static/assets/index-sMIa_1hV.css
ui/__init__.py
ui/acquisition_panel.py
ui/custom_widgets.py
ui/experiment_logger.py
ui/gpr_panel.py
ui/notifications.py
ui/pool_viz.py
ui/ui.py
ui/ui_utils.py
ui/utils.py
ui/variables_setup.py
ui/visualizations.py
alchemist_nrel-0.3.1.dist-info/METADATA
alchemist_nrel-0.3.1.dist-info/WHEEL
alchemist_nrel-0.3.1.dist-info/entry_points.txt
alchemist_nrel-0.3.1.dist-info/top_level.txt
alchemist_nrel-0.3.1.dist-info/RECORD
