Metadata-Version: 2.4
Name: alchemist-nrel
Version: 0.3.1
Summary: Active learning and optimization toolkit for chemical and materials research
Author-email: Caleb Coatney <caleb.coatney@nrel.gov>
License: BSD-3-Clause
Project-URL: Homepage, https://github.com/NREL/ALchemist
Project-URL: Documentation, https://nrel.github.io/ALchemist/
Project-URL: Source, https://github.com/NREL/ALchemist
Project-URL: Bug Tracker, https://github.com/NREL/ALchemist/issues
Project-URL: Changelog, https://github.com/NREL/ALchemist/releases
Keywords: active learning,bayesian optimization,gaussian processes,materials science,chemistry
Classifier: Development Status :: 4 - Beta
Classifier: Intended Audience :: Science/Research
Classifier: License :: OSI Approved :: BSD License
Classifier: Operating System :: OS Independent
Classifier: Programming Language :: Python :: 3
Classifier: Programming Language :: Python :: 3.11
Classifier: Programming Language :: Python :: 3.12
Classifier: Topic :: Scientific/Engineering
Classifier: Topic :: Scientific/Engineering :: Chemistry
Requires-Python: >=3.11
License-File: LICENSE
Requires-Dist: numpy
Requires-Dist: pandas
Requires-Dist: scipy
Requires-Dist: matplotlib
Requires-Dist: mplcursors
Requires-Dist: scikit-learn
Requires-Dist: scikit-optimize
Requires-Dist: botorch
Requires-Dist: torch
Requires-Dist: gpytorch
Requires-Dist: ax-platform
Requires-Dist: customtkinter
Requires-Dist: tksheet
Requires-Dist: tabulate
Requires-Dist: ctkmessagebox
Requires-Dist: joblib
Requires-Dist: fastapi>=0.109.0
Requires-Dist: uvicorn[standard]>=0.27.0
Requires-Dist: pydantic>=2.5.0
Requires-Dist: python-multipart>=0.0.6
Requires-Dist: requests
Provides-Extra: test
Requires-Dist: pytest>=8.0.0; extra == "test"
Requires-Dist: pytest-cov>=4.0.0; extra == "test"
Requires-Dist: pytest-anyio>=0.0.0; extra == "test"
Requires-Dist: httpx>=0.25.0; extra == "test"
Requires-Dist: requests>=2.31.0; extra == "test"
Provides-Extra: dev
Requires-Dist: pytest>=8.0.0; extra == "dev"
Requires-Dist: pytest-cov>=4.0.0; extra == "dev"
Requires-Dist: pytest-anyio>=0.0.0; extra == "dev"
Requires-Dist: httpx>=0.25.0; extra == "dev"
Requires-Dist: requests>=2.31.0; extra == "dev"
Dynamic: license-file
